[
    {
        "id": 1,
        "src": "jpeg_images/image_1.jpeg"
    },
    {
        "id": 2,
        "src": "jpeg_images/image_2.jpeg"
    },
    {
        "id": 3,
        "src": "jpeg_images/image_3.jpeg"
    },
    {
        "id": 4,
        "src": "jpeg_images/image_4.jpeg"
    },
    {
        "id": 5,
        "src": "jpeg_images/image_5.jpeg"
    },
    {
        "id": 6,
        "src": "jpeg_images/image_6.jpeg"
    },
    {
        "id": 7,
        "src": "jpeg_images/image_7.jpeg"
    },
    {
        "id": 8,
        "src": "jpeg_images/image_8.jpeg"
    },
    {
        "id": 9,
        "src": "jpeg_images/image_9.jpeg"
    },
    {
        "id": 10,
        "src": "jpeg_images/image_10.jpeg"
    },
    {
        "id": 11,
        "src": "jpeg_images/image_11.jpeg"
    },
    {
        "id": 12,
        "src": "jpeg_images/image_12.jpeg"
    },
    {
        "id": 13,
        "src": "jpeg_images/image_13.jpeg"
    },
    {
        "id": 14,
        "src": "jpeg_images/image_14.jpeg"
    },
    {
        "id": 15,
        "src": "jpeg_images/image_15.jpeg"
    },
    {
        "id": 16,
        "src": "jpeg_images/image_16.jpeg"
    },
    {
        "id": 17,
        "src": "jpeg_images/image_17.jpeg"
    },
    {
        "id": 18,
        "src": "jpeg_images/image_18.jpeg"
    },
    {
        "id": 19,
        "src": "jpeg_images/image_19.jpeg"
    },
    {
        "id": 20,
        "src": "jpeg_images/image_20.jpeg"
    },
    {
        "id": 21,
        "src": "jpeg_images/image_21.jpeg"
    },
    {
        "id": 22,
        "src": "jpeg_images/image_22.jpeg"
    },
    {
        "id": 23,
        "src": "jpeg_images/image_23.jpeg"
    },
    {
        "id": 24,
        "src": "jpeg_images/image_24.jpeg"
    },
    {
        "id": 25,
        "src": "jpeg_images/image_25.jpeg"
    },
    {
        "id": 26,
        "src": "jpeg_images/image_26.jpeg"
    },
    {
        "id": 27,
        "src": "jpeg_images/image_27.jpeg"
    },
    {
        "id": 28,
        "src": "jpeg_images/image_28.jpeg"
    },
    {
        "id": 29,
        "src": "jpeg_images/image_29.jpeg"
    },
    {
        "id": 30,
        "src": "jpeg_images/image_30.jpeg"
    },
    {
        "id": 31,
        "src": "jpeg_images/image_31.jpeg"
    },
    {
        "id": 32,
        "src": "jpeg_images/image_32.jpeg"
    },
    {
        "id": 33,
        "src": "jpeg_images/image_33.jpeg"
    }
]